kerko/__init__.py
kerko/blueprint.py
kerko/cli.py
kerko/codecs.py
kerko/composer.py
kerko/config_helpers.py
kerko/criteria.py
kerko/datetime.py
kerko/default_config.toml
kerko/exceptions.py
kerko/extractors.py
kerko/forms.py
kerko/jinja2.py
kerko/renderers.py
kerko/richtext.py
kerko/searcher.py
kerko/shortcuts.py
kerko/specs.py
kerko/storage.py
kerko/tags.py
kerko/text.py
kerko/transformers.py
kerko/tree.py
kerko/static/kerko/css/styles.css
kerko/static/kerko/js/item.js
kerko/static/kerko/js/open_in_zotero.js
kerko/static/kerko/js/print.js
kerko/static/kerko/js/search.js
kerko/sync/__init__.py
kerko/sync/attachments.py
kerko/sync/cache.py
kerko/sync/index.py
kerko/sync/zotero.py
kerko/templates/kerko/_attributes.html.jinja2
kerko/templates/kerko/_badges.html.jinja2
kerko/templates/kerko/_breadbox.html.jinja2
kerko/templates/kerko/_breadcrumb.html.jinja2
kerko/templates/kerko/_collapse.html.jinja2
kerko/templates/kerko/_facet_breadbox.html.jinja2
kerko/templates/kerko/_facet_field.html.jinja2
kerko/templates/kerko/_facet_search.html.jinja2
kerko/templates/kerko/_facets.html.jinja2
kerko/templates/kerko/_item-relations.html.jinja2
kerko/templates/kerko/_navbar_brand.html.jinja2
kerko/templates/kerko/_navbar_items.html.jinja2
kerko/templates/kerko/_pager.html.jinja2
kerko/templates/kerko/_preferences.html.jinja2
kerko/templates/kerko/_search-form.html.jinja2
kerko/templates/kerko/_search-help.html.jinja2
kerko/templates/kerko/_search-metas.html.jinja2
kerko/templates/kerko/_search-result.html.jinja2
kerko/templates/kerko/_sorter.html.jinja2
kerko/templates/kerko/atom.xml.jinja2
kerko/templates/kerko/base.html.jinja2
kerko/templates/kerko/item.html.jinja2
kerko/templates/kerko/layout.html.jinja2
kerko/templates/kerko/page.html.jinja2
kerko/templates/kerko/search-item.html.jinja2
kerko/templates/kerko/search.html.jinja2
kerko/templates/kerko/sitemap.xml.jinja2
kerko/templates/kerko/sitemap_index.xml.jinja2
kerko/translations/de/LC_MESSAGES/kerko.mo
kerko-1.3.0.dist-info/METADATA
kerko-1.3.0.dist-info/WHEEL
kerko-1.3.0.dist-info/entry_points.txt
kerko-1.3.0.dist-info/licenses/LICENSE.txt
kerko-1.3.0.dist-info/RECORD
