Metadata-Version: 2.4
Name: Kerko
Version: 1.3.0
Summary: A Flask blueprint that provides a faceted search interface for bibliographies based on Zotero.
Project-URL: Documentation, https://whiskyechobravo.github.io/kerko/
Project-URL: Code, https://github.com/whiskyechobravo/kerko
Project-URL: Changes, https://github.com/whiskyechobravo/kerko/blob/main/CHANGELOG.md
Project-URL: Issues, https://github.com/whiskyechobravo/kerko/issues
Author-email: David Lesieur <kerko@whiskyechobravo.com>
License-Expression: GPL-3.0-only
License-File: LICENSE.txt
Keywords: academia,bibliographies,bibliography,flask,search,zotero
Classifier: Development Status :: 5 - Production/Stable
Classifier: Environment :: Web Environment
Classifier: Framework :: Flask
Classifier: Intended Audience :: Developers
Classifier: Intended Audience :: Education
Classifier: Intended Audience :: Science/Research
Classifier: Operating System :: OS Independent
Classifier: Programming Language :: Python
Classifier: Programming Language :: Python :: 3
Classifier: Programming Language :: Python :: 3.9
Classifier: Programming Language :: Python :: 3.10
Classifier: Programming Language :: Python :: 3.11
Classifier: Programming Language :: Python :: 3.12
Classifier: Programming Language :: Python :: 3.13
Classifier: Topic :: Database :: Front-Ends
Classifier: Topic :: Education
Classifier: Topic :: Internet :: WWW/HTTP :: Dynamic Content
Classifier: Topic :: Internet :: WWW/HTTP :: Indexing/Search
Classifier: Topic :: Internet :: WWW/HTTP :: WSGI :: Application
Classifier: Topic :: Scientific/Engineering
Classifier: Topic :: Software Development :: Libraries :: Python Modules
Requires-Python: >=3.9
Requires-Dist: babel>=2.14.0
Requires-Dist: bootstrap-flask>=2.0.1
Requires-Dist: click>=8.0.1
Requires-Dist: dpath>=2.1.0
Requires-Dist: flask-babel>=3.0.1
Requires-Dist: flask-wtf>=0.14.2
Requires-Dist: flask>=2.2.5
Requires-Dist: jinja2>=3.0.1
Requires-Dist: pycountry>=24
Requires-Dist: pydantic>=2.11.5
Requires-Dist: python-dotenv>=0.21.1
Requires-Dist: pytz
Requires-Dist: pyzotero<=1.5.20,>=1.4.26
Requires-Dist: tomli-w>=1.0.0
Requires-Dist: tomli>=2.0.1
Requires-Dist: w3lib>=1.22.0
Requires-Dist: werkzeug>=2.0.1
Requires-Dist: whoosh>=2.7.4
Requires-Dist: wrapt>=1.10.0
Requires-Dist: wtforms>=3.0.0
Provides-Extra: dev
Requires-Dist: pip-tools>=5.5.0; extra == 'dev'
Requires-Dist: pre-commit>=3.5.0; extra == 'dev'
Requires-Dist: rope; extra == 'dev'
Requires-Dist: ruff>=0.1.3; extra == 'dev'
Provides-Extra: docs
Requires-Dist: mike<3,>=1.1.2; extra == 'docs'
Requires-Dist: mkdocs-material<10,>=9.4; extra == 'docs'
Provides-Extra: tests
Requires-Dist: coverage<8,>=6.1.2; extra == 'tests'
Requires-Dist: elementpath<6,>=5; extra == 'tests'
Requires-Dist: lxml<6,>=5.0.2; extra == 'tests'
Requires-Dist: responses>=0.17.0; extra == 'tests'
Requires-Dist: tox<5,>=4.24.2; extra == 'tests'
